cron_validator/__init__.py
cron_validator/regexes.py
cron_validator/scheduler.py
cron_validator/util.py
cron_validator/validator.py
cron_validator-1.0.8.dist-info/LICENSE.txt
cron_validator-1.0.8.dist-info/METADATA
cron_validator-1.0.8.dist-info/WHEEL
cron_validator-1.0.8.dist-info/top_level.txt
cron_validator-1.0.8.dist-info/RECORD
