Metadata-Version: 2.1
Name: cron-validator
Version: 1.0.8
Summary: Unix cron implementation by Python
Home-page: https://github.com/vcoder4c/cron-validator
Author: vcoder
Author-email: doanngocbao@gmail.com
License: MIT
Download-URL: https://github.com/vcoder4c/cron-validator/archive/v1.0.8.tar.gz
Keywords: cron,python,cron expression validator,cron expression iterator,cron scheduler
Platform: UNKNOWN
License-File: LICENSE.txt
